leaone_ble/__init__.py
leaone_ble/parser.py
leaone_ble/py.typed
leaone_ble-1.0.0.dist-info/METADATA
leaone_ble-1.0.0.dist-info/WHEEL
leaone_ble-1.0.0.dist-info/licenses/LICENSE
leaone_ble-1.0.0.dist-info/RECORD
